scriptplan/__init__.py
scriptplan/py.typed
scriptplan/_cython/__init__.py
scriptplan/_cython/scoreboard_cy.c
scriptplan/_cython/scoreboard_cy.cpython-314-x86_64-linux-musl.so
scriptplan/_cython/scoreboard_cy.pyx
scriptplan/_cython/time_utils_cy.c
scriptplan/_cython/time_utils_cy.cpython-314-x86_64-linux-musl.so
scriptplan/_cython/time_utils_cy.pyx
scriptplan/_cython/working_hours_cy.c
scriptplan/_cython/working_hours_cy.cpython-314-x86_64-linux-musl.so
scriptplan/_cython/working_hours_cy.pyx
scriptplan/cli/__init__.py
scriptplan/cli/main.py
scriptplan/cli/plan.py
scriptplan/core/__init__.py
scriptplan/core/account.py
scriptplan/core/allocation.py
scriptplan/core/booking.py
scriptplan/core/exceptions.py
scriptplan/core/journal.py
scriptplan/core/leave.py
scriptplan/core/limits.py
scriptplan/core/project.py
scriptplan/core/property.py
scriptplan/core/resource.py
scriptplan/core/resource_scenario.py
scriptplan/core/scenario.py
scriptplan/core/scenario_data.py
scriptplan/core/shift.py
scriptplan/core/task.py
scriptplan/core/task_scenario.py
scriptplan/core/timesheet.py
scriptplan/core/working_hours.py
scriptplan/parser/__init__.py
scriptplan/parser/macro_processor.py
scriptplan/parser/tjp.lark
scriptplan/parser/tjp_parser.py
scriptplan/report/__init__.py
scriptplan/report/report.py
scriptplan/report/report_base.py
scriptplan/report/report_context.py
scriptplan/report/resource_report.py
scriptplan/report/table_report.py
scriptplan/report/task_report.py
scriptplan/report/text_report.py
scriptplan/scheduler/__init__.py
scriptplan/scheduler/batch_processor.py
scriptplan/scheduler/scoreboard.py
scriptplan/utils/__init__.py
scriptplan/utils/data_cache.py
scriptplan/utils/logger.py
scriptplan/utils/message_handler.py
scriptplan/utils/time.py
scriptplan-0.9.2.dist-info/METADATA
scriptplan-0.9.2.dist-info/WHEEL
scriptplan-0.9.2.dist-info/entry_points.txt
scriptplan-0.9.2.dist-info/top_level.txt
scriptplan-0.9.2.dist-info/RECORD
scriptplan-0.9.2.dist-info/licenses/LICENSE
