Metadata-Version: 2.4
Name: scriptplan
Version: 0.9.2
Summary: A precise project scheduling engine with minute-level accuracy for resource allocation and dependency management.
Author-email: Farshid Ashouri <farsheed.ashouri@gmail.com>
Maintainer-email: Farshid Ashouri <farsheed.ashouri@gmail.com>
License-Expression: Apache-2.0
Project-URL: Homepage, https://github.com/rodmena-limited/scriptplan
Project-URL: Documentation, https://github.com/rodmena-limited/scriptplan#readme
Project-URL: Bug Tracker, https://github.com/rodmena-limited/scriptplan/issues
Project-URL: Source, https://github.com/rodmena-limited/scriptplan
Keywords: scheduling,project-management,resource-allocation,gantt,critical-path
Classifier: Development Status :: 4 - Beta
Classifier: Intended Audience :: Developers
Classifier: Intended Audience :: Information Technology
Classifier: Programming Language :: Python :: 3
Classifier: Programming Language :: Python :: 3.9
Classifier: Programming Language :: Python :: 3.10
Classifier: Programming Language :: Python :: 3.11
Classifier: Programming Language :: Python :: 3.12
Classifier: Programming Language :: Python :: 3.13
Classifier: Programming Language :: Python :: 3.14
Classifier: Operating System :: OS Independent
Classifier: Topic :: Office/Business :: Scheduling
Classifier: Topic :: Software Development :: Libraries :: Python Modules
Classifier: Typing :: Typed
Requires-Python: >=3.9
License-File: LICENSE
Requires-Dist: lark>=1.0.0
Requires-Dist: python-dateutil>=2.8.0
Requires-Dist: click>=8.0.0
Provides-Extra: dev
Requires-Dist: pytest>=7.0.0; extra == "dev"
Requires-Dist: pytest-xdist>=3.0.0; extra == "dev"
Requires-Dist: pandas>=1.5.0; extra == "dev"
Requires-Dist: types-python-dateutil>=2.8.0; extra == "dev"
Requires-Dist: types-pytz>=2022.1.0; extra == "dev"
Requires-Dist: build; extra == "dev"
Requires-Dist: twine; extra == "dev"
Requires-Dist: ruff>=0.1.0; extra == "dev"
Requires-Dist: mypy>=1.0.0; extra == "dev"
Requires-Dist: cython>=3.0.0; extra == "dev"
Dynamic: license-file
